Metadata-Version: 2.1
Name: panpiper
Version: 1.0.2
Summary: Panpiper: snakemake workflow for bacterial isolate analysis
Home-page: https://github.com/rolesucsd/Panpiper
Author: Renee Oles
Author-email: roles@health.ucsd.edu
License: BSD-3-Clause
Classifier: Programming Language :: Python :: 3
Classifier: License :: OSI Approved :: MIT License
Classifier: Operating System :: OS Independent
Classifier: Topic :: Software Development :: Libraries :: Python Modules
Classifier: Development Status :: 3 - Alpha
Requires-Python: >=3.5
License-File: LICENSE
Requires-Dist: setuptools
Requires-Dist: matplotlib
Requires-Dist: seaborn
Requires-Dist: scikit-learn
Requires-Dist: umap-learn
Requires-Dist: biopython
